sfctss/__init__.py
sfctss/events.py
sfctss/measurement.py
sfctss/meta.json
sfctss/rate_estimator.py
sfctss/sanity.py
sfctss/simulator.py
sfctss/ui.py
sfctss/workload.py
sfctss/model/__init__.py
sfctss/model/core.py
sfctss/model/server.py
sfctss/model/sff.py
sfctss/model/sfi.py
sfctss/scheduler/__init__.py
sfctss/scheduler/core.py
sfctss/scheduler/examples.py
sfctss-1.0.0.dist-info/LICENSE
sfctss-1.0.0.dist-info/METADATA
sfctss-1.0.0.dist-info/WHEEL
sfctss-1.0.0.dist-info/top_level.txt
sfctss-1.0.0.dist-info/RECORD
