Metadata-Version: 2.1
Name: sfctss
Version: 1.0.0
Summary: A Service Function Chain (SFC) Traffic Scheduling Simulator
Home-page: https://github.com/mblo/sfctss
Author: Marcel Blöcher
License: Apache 2.0
Platform: UNKNOWN
Classifier: Intended Audience :: Developers
Classifier: License :: OSI Approved :: Apache Software License
Classifier: Programming Language :: Python :: Implementation :: CPython
Classifier: Programming Language :: Python :: Implementation :: PyPy
Classifier: Programming Language :: Python :: 3
Classifier: Programming Language :: Python :: 3.6
Classifier: Programming Language :: Python :: 3.7
Classifier: Programming Language :: Python :: 3.8
Requires-Python: >=3.6, <4
Requires-Dist: numpy (>=1.19.5)
Requires-Dist: sortedcontainers (>=2.3.0)
Requires-Dist: terminaltables (>=3.1.0)
